[{"manufacturer":"HTC","type":"One","price":30000,"color":"WHITE","count":0},{"manufacturer":"HTC","type":"Two","price":30000,"color":"WHITE","count":0},{"manufacturer":"HTC","type":"Three","price":30000,"color":"WHITE","count":0},{"manufacturer":"HTC","type":"Four","price":30000,"color":"WHITE","count":0},{"manufacturer":"HTC","type":"Five","price":30000,"color":"WHITE","count":0},{"manufacturer":"HTC","type":"Six","price":30000,"color":"WHITE","count":0},{"manufacturer":"HTC","type":"Seven","price":30000,"color":"WHITE","count":0},{"manufacturer":"HTC","type":"Eight","price":30000,"color":"WHITE","count":0},{"manufacturer":"HTC","type":"Nine","price":30000,"color":"WHITE","count":0},{"manufacturer":"HTC","type":"Ten","price":30000,"color":"WHITE","count":0}]